{
  "version": "4.5.13",
  "flags": {},
  "shapes": [
    {
      "label": "corners",
      "points": [
        [
          120.13286713286715,
          579.4195804195805
        ],
        [
          778.8741258741259,
          580.1188811188812
        ],
        [
          694.958041958042,
          218.5804195804196
        ],
        [
          427.12587412587413,
          216.4825174825175
        ],
        [
          406.1468531468532,
          214.3846153846154
        ],
        [
          397.7552447552448,
          220.67832167832168
        ],
        [
          387.965034965035,
          228.3706293706294
        ],
        [
          215.93706293706293,
          326.2727272727273
        ],
        [
          185.86713286713288,
          306.6923076923077
        ]
      ],
      "group_id": null,
      "shape_type": "polygon",
      "flags": {}
    }
  ],
  "imagePath": "0029.jpg",
  "imageData": null,
  "imageHeight": 675,
  "imageWidth": 900
}